auth/__init__.py
auth/auth.py
mpesa/__init__.py
mpesa/api.py
tests/__init__.py
tests/test_account_balance.py
tests/test_async_ussd_push.py
tests/test_auth.py
tests/test_customer_initiated_payment.py
tests/test_my_pay_out.py
tests/test_pay_out.py
tests/test_register.py
payment_sdk-0.1.0.dist-info/METADATA
payment_sdk-0.1.0.dist-info/WHEEL
payment_sdk-0.1.0.dist-info/top_level.txt
payment_sdk-0.1.0.dist-info/RECORD
